notebattle/__init__.py
notebattle/battles/__init__.py
notebattle/battles/datafountain/__init__.py
notebattle/battles/datafountain/bt557/__init__.py
notebattle/battles/datafountain/bt557/evalution/__init__.py
notebattle/battles/datafountain/bt557/model/__init__.py
notebattle/battles/datafountain/bt557/utils/__init__.py
notebattle-0.0.6.dist-info/METADATA
notebattle-0.0.6.dist-info/WHEEL
notebattle-0.0.6.dist-info/top_level.txt
notebattle-0.0.6.dist-info/RECORD
