Metadata-Version: 2.1
Name: notebattle
Version: 0.0.6
Summary: notebattle
Home-page: https://github.com/1007530194
Author: bingtao
Author-email: 1007530194@qq.com
License: UNKNOWN
Platform: UNKNOWN
Requires-Dist: tqdm
